{
  "project": {
    "title": "Sistem Analisis Serangan DoS pada Arsitektur IoT",
    "theme": "IoT + Cyber Security + Digital Forensics",
    "primary_dataset": "BoT-IoT (UNSW)",
    "alternative_dataset": "RT-IoT2022 (UCI)",
    "status": "Fase 4 Baseline Modeling completed; technical review pending"
  },
  "dataset_summary": {
    "source": "Mireu-Lab/UNSW-IoT Hugging Face mirror",
    "official_primary_source": "https://research.unsw.edu.au/projects/bot-iot-dataset",
    "working_mirror": "https://huggingface.co/datasets/Mireu-Lab/UNSW-IoT",
    "rows": 3668522,
    "files": 2,
    "bytes": 461384981,
    "columns": 19,
    "candidate_features": 10,
    "excluded_columns": [
      "attack",
      "category",
      "daddr",
      "dport",
      "pkSeqID",
      "saddr",
      "seq",
      "sport",
      "subcategory"
    ]
  },
  "class_distribution": [
    {
      "split": "train",
      "group": "category_counts",
      "label": "DDoS",
      "count": 1541315,
      "rate": 0.52518266
    },
    {
      "split": "train",
      "group": "category_counts",
      "label": "DoS",
      "count": 1320148,
      "rate": 0.44982294
    },
    {
      "split": "train",
      "group": "category_counts",
      "label": "Normal",
      "count": 370,
      "rate": 0.00012607
    },
    {
      "split": "train",
      "group": "category_counts",
      "label": "Reconnaissance",
      "count": 72919,
      "rate": 0.02484618
    },
    {
      "split": "train",
      "group": "category_counts",
      "label": "Theft",
      "count": 65,
      "rate": 2.215e-05
    },
    {
      "split": "train",
      "group": "dos_scope_counts",
      "label": "dos_or_ddos",
      "count": 2861463,
      "rate": 0.9750056
    },
    {
      "split": "train",
      "group": "dos_scope_counts",
      "label": "normal",
      "count": 370,
      "rate": 0.00012607
    },
    {
      "split": "train",
      "group": "dos_scope_counts",
      "label": "other_attack",
      "count": 72984,
      "rate": 0.02486833
    },
    {
      "split": "test",
      "group": "category_counts",
      "label": "DDoS",
      "count": 385309,
      "rate": 0.52515521
    },
    {
      "split": "test",
      "group": "category_counts",
      "label": "DoS",
      "count": 330112,
      "rate": 0.4499247
    },
    {
      "split": "test",
      "group": "category_counts",
      "label": "Normal",
      "count": 107,
      "rate": 0.00014584
    },
    {
      "split": "test",
      "group": "category_counts",
      "label": "Reconnaissance",
      "count": 18163,
      "rate": 0.02475518
    },
    {
      "split": "test",
      "group": "category_counts",
      "label": "Theft",
      "count": 14,
      "rate": 1.908e-05
    },
    {
      "split": "test",
      "group": "dos_scope_counts",
      "label": "dos_or_ddos",
      "count": 715421,
      "rate": 0.9750799
    },
    {
      "split": "test",
      "group": "dos_scope_counts",
      "label": "normal",
      "count": 107,
      "rate": 0.00014584
    },
    {
      "split": "test",
      "group": "dos_scope_counts",
      "label": "other_attack",
      "count": 18177,
      "rate": 0.02477426
    }
  ],
  "eda_summary": {
    "total_rows": 3668522,
    "candidate_features": [
      "proto",
      "stddev",
      "N_IN_Conn_P_SrcIP",
      "min",
      "state_number",
      "mean",
      "N_IN_Conn_P_DstIP",
      "drate",
      "srate",
      "max"
    ],
    "excluded_columns": [
      "attack",
      "category",
      "daddr",
      "dport",
      "pkSeqID",
      "saddr",
      "seq",
      "sport",
      "subcategory"
    ],
    "recommended_phase4_tracks": [
      "A_realistic_imbalanced",
      "B_balanced_controlled_1_to_1",
      "C_balanced_controlled_1_to_2",
      "optional_DoS_vs_DDoS_or_protocol_subtype_forensic_analysis"
    ],
    "warnings": [
      "Normal class is extremely small; accuracy alone is not acceptable.",
      "Network identifiers and label columns must remain excluded from model features.",
      "Other attacks must not be silently mapped to normal in the primary binary task.",
      "Feature-signature similarity from Fase 2 should be disclosed when interpreting future model performance."
    ],
    "scope_counts": {
      "test": {
        "dos_or_ddos": 715421,
        "normal": 107,
        "other_attack": 18177
      },
      "train": {
        "dos_or_ddos": 2861463,
        "normal": 370,
        "other_attack": 72984
      }
    },
    "dataset_plan": [
      {
        "track": "A_realistic_imbalanced",
        "split": "test",
        "normal_rows": "107",
        "dos_or_ddos_rows": "715421",
        "other_attack_rows": "18177",
        "other_attack_policy": "exclude_from_binary_baseline",
        "dos_sample_rows": "715421",
        "target_ratio_normal_to_dos": "1:6686.18",
        "random_state": "none",
        "purpose": "Reflect audited distribution; evaluate with precision, recall, F1, confusion matrix, not accuracy alone."
      },
      {
        "track": "B_balanced_controlled_1_to_1",
        "split": "test",
        "normal_rows": "107",
        "dos_or_ddos_rows": "715421",
        "other_attack_rows": "18177",
        "other_attack_policy": "exclude_from_binary_baseline",
        "dos_sample_rows": "107",
        "target_ratio_normal_to_dos": "1:1",
        "random_state": "42",
        "purpose": "Control imbalance so Fase 4 can test feature separability without majority-class dominance."
      },
      {
        "track": "C_balanced_controlled_1_to_2",
        "split": "test",
        "normal_rows": "107",
        "dos_or_ddos_rows": "715421",
        "other_attack_rows": "18177",
        "other_attack_policy": "exclude_from_binary_baseline",
        "dos_sample_rows": "214",
        "target_ratio_normal_to_dos": "1:2",
        "random_state": "42",
        "purpose": "Moderately imbalanced sensitivity check; still prevents millions of attacks from dominating."
      },
      {
        "track": "A_realistic_imbalanced",
        "split": "train",
        "normal_rows": "370",
        "dos_or_ddos_rows": "2861463",
        "other_attack_rows": "72984",
        "other_attack_policy": "exclude_from_binary_baseline",
        "dos_sample_rows": "2861463",
        "target_ratio_normal_to_dos": "1:7733.68",
        "random_state": "none",
        "purpose": "Reflect audited distribution; evaluate with precision, recall, F1, confusion matrix, not accuracy alone."
      },
      {
        "track": "B_balanced_controlled_1_to_1",
        "split": "train",
        "normal_rows": "370",
        "dos_or_ddos_rows": "2861463",
        "other_attack_rows": "72984",
        "other_attack_policy": "exclude_from_binary_baseline",
        "dos_sample_rows": "370",
        "target_ratio_normal_to_dos": "1:1",
        "random_state": "42",
        "purpose": "Control imbalance so Fase 4 can test feature separability without majority-class dominance."
      },
      {
        "track": "C_balanced_controlled_1_to_2",
        "split": "train",
        "normal_rows": "370",
        "dos_or_ddos_rows": "2861463",
        "other_attack_rows": "72984",
        "other_attack_policy": "exclude_from_binary_baseline",
        "dos_sample_rows": "740",
        "target_ratio_normal_to_dos": "1:2",
        "random_state": "42",
        "purpose": "Moderately imbalanced sensitivity check; still prevents millions of attacks from dominating."
      }
    ],
    "figures": [
      "results/figures/eda_category_distribution_log.png",
      "results/figures/eda_binary_scope_distribution_log.png",
      "results/figures/eda_protocol_by_scope_log.png",
      "results/figures/eda_numeric_feature_means_log.png"
    ]
  },
  "model_comparison": [
    {
      "track": "B_balanced_controlled_1_to_1",
      "model": "random_forest",
      "model_display_name": "Random Forest",
      "model_family": "ensemble_baseline",
      "macro_f1": 1.0,
      "mcc": 1.0,
      "balanced_accuracy": 1.0,
      "precision_attack": 1.0,
      "recall_attack": 1.0,
      "precision_normal": 1.0,
      "recall_normal": 1.0,
      "accuracy": 1.0
    },
    {
      "track": "C_balanced_controlled_1_to_2",
      "model": "random_forest",
      "model_display_name": "Random Forest",
      "model_family": "ensemble_baseline",
      "macro_f1": 1.0,
      "mcc": 1.0,
      "balanced_accuracy": 1.0,
      "precision_attack": 1.0,
      "recall_attack": 1.0,
      "precision_normal": 1.0,
      "recall_normal": 1.0,
      "accuracy": 1.0
    },
    {
      "track": "B_balanced_controlled_1_to_1",
      "model": "decision_tree",
      "model_display_name": "Decision Tree",
      "model_family": "tree_baseline",
      "macro_f1": 0.995327,
      "mcc": 0.99069747,
      "balanced_accuracy": 0.9953271,
      "precision_attack": 1.0,
      "recall_attack": 0.99065421,
      "precision_normal": 0.99074074,
      "recall_normal": 1.0,
      "accuracy": 0.9953271
    },
    {
      "track": "B_balanced_controlled_1_to_1",
      "model": "sgd_logistic",
      "model_display_name": "SGD Logistic Regression",
      "model_family": "linear_baseline",
      "macro_f1": 0.99065339,
      "mcc": 0.98147988,
      "balanced_accuracy": 0.99065421,
      "precision_attack": 1.0,
      "recall_attack": 0.98130841,
      "precision_normal": 0.98165138,
      "recall_normal": 1.0,
      "accuracy": 0.99065421
    },
    {
      "track": "C_balanced_controlled_1_to_2",
      "model": "decision_tree",
      "model_display_name": "Decision Tree",
      "model_family": "tree_baseline",
      "macro_f1": 0.98955815,
      "mcc": 0.97933187,
      "balanced_accuracy": 0.99299065,
      "precision_attack": 1.0,
      "recall_attack": 0.98598131,
      "precision_normal": 0.97272727,
      "recall_normal": 1.0,
      "accuracy": 0.99065421
    },
    {
      "track": "C_balanced_controlled_1_to_2",
      "model": "sgd_logistic",
      "model_display_name": "SGD Logistic Regression",
      "model_family": "linear_baseline",
      "macro_f1": 0.98610871,
      "mcc": 0.97259753,
      "balanced_accuracy": 0.99065421,
      "precision_attack": 1.0,
      "recall_attack": 0.98130841,
      "precision_normal": 0.96396396,
      "recall_normal": 1.0,
      "accuracy": 0.98753894
    },
    {
      "track": "A_realistic_imbalanced",
      "model": "decision_tree",
      "model_display_name": "Decision Tree",
      "model_family": "tree_baseline",
      "macro_f1": 0.96666142,
      "mcc": 0.93444061,
      "balanced_accuracy": 0.99064512,
      "precision_attack": 0.9999972,
      "recall_attack": 0.99998183,
      "precision_normal": 0.88983051,
      "recall_normal": 0.98130841,
      "accuracy": 0.99997904
    },
    {
      "track": "C_balanced_controlled_1_to_2",
      "model": "gaussian_nb",
      "model_display_name": "Gaussian Naive Bayes",
      "model_family": "probabilistic_baseline",
      "macro_f1": 0.93775167,
      "mcc": 0.88273483,
      "balanced_accuracy": 0.92056075,
      "precision_attack": 0.92640693,
      "recall_attack": 1.0,
      "precision_normal": 1.0,
      "recall_normal": 0.8411215,
      "accuracy": 0.9470405
    },
    {
      "track": "B_balanced_controlled_1_to_1",
      "model": "gaussian_nb",
      "model_display_name": "Gaussian Naive Bayes",
      "model_family": "probabilistic_baseline",
      "macro_f1": 0.86195084,
      "mcc": 0.75731725,
      "balanced_accuracy": 0.86448598,
      "precision_attack": 0.78676471,
      "recall_attack": 1.0,
      "precision_normal": 1.0,
      "recall_normal": 0.72897196,
      "accuracy": 0.86448598
    },
    {
      "track": "A_realistic_imbalanced",
      "model": "gaussian_nb",
      "model_display_name": "Gaussian Naive Bayes",
      "model_family": "probabilistic_baseline",
      "macro_f1": 0.54119336,
      "mcc": 0.10641014,
      "balanced_accuracy": 0.61183573,
      "precision_attack": 0.99988393,
      "recall_attack": 0.9993724,
      "precision_normal": 0.05073996,
      "recall_normal": 0.22429907,
      "accuracy": 0.99925649
    },
    {
      "track": "A_realistic_imbalanced",
      "model": "sgd_logistic",
      "model_display_name": "SGD Logistic Regression",
      "model_family": "linear_baseline",
      "macro_f1": 0.51150222,
      "mcc": 0.11894466,
      "balanced_accuracy": 0.9948436,
      "precision_attack": 1.0,
      "recall_attack": 0.98968719,
      "precision_normal": 0.01429526,
      "recall_normal": 1.0,
      "accuracy": 0.98968873
    },
    {
      "track": "A_realistic_imbalanced",
      "model": "dummy_majority",
      "model_display_name": "Dummy Majority",
      "model_family": "sanity_baseline",
      "macro_f1": 0.49996261,
      "mcc": 0.0,
      "balanced_accuracy": 0.5,
      "precision_attack": 0.99985046,
      "recall_attack": 1.0,
      "precision_normal": 0.0,
      "recall_normal": 0.0,
      "accuracy": 0.99985046
    },
    {
      "track": "C_balanced_controlled_1_to_2",
      "model": "dummy_majority",
      "model_display_name": "Dummy Majority",
      "model_family": "sanity_baseline",
      "macro_f1": 0.4,
      "mcc": 0.0,
      "balanced_accuracy": 0.5,
      "precision_attack": 0.66666667,
      "recall_attack": 1.0,
      "precision_normal": 0.0,
      "recall_normal": 0.0,
      "accuracy": 0.66666667
    },
    {
      "track": "B_balanced_controlled_1_to_1",
      "model": "dummy_majority",
      "model_display_name": "Dummy Majority",
      "model_family": "sanity_baseline",
      "macro_f1": 0.33333333,
      "mcc": 0.0,
      "balanced_accuracy": 0.5,
      "precision_attack": 0.0,
      "recall_attack": 0.0,
      "precision_normal": 0.5,
      "recall_normal": 1.0,
      "accuracy": 0.5
    }
  ],
  "confusion_matrix": [
    {
      "track": "A_realistic_imbalanced",
      "model": "dummy_majority",
      "tn_normal_correct": 0,
      "fp_normal_as_attack": 107,
      "fn_attack_as_normal": 0,
      "tp_attack_correct": 715421
    },
    {
      "track": "A_realistic_imbalanced",
      "model": "gaussian_nb",
      "tn_normal_correct": 24,
      "fp_normal_as_attack": 83,
      "fn_attack_as_normal": 449,
      "tp_attack_correct": 714972
    },
    {
      "track": "A_realistic_imbalanced",
      "model": "sgd_logistic",
      "tn_normal_correct": 107,
      "fp_normal_as_attack": 0,
      "fn_attack_as_normal": 7378,
      "tp_attack_correct": 708043
    },
    {
      "track": "A_realistic_imbalanced",
      "model": "decision_tree",
      "tn_normal_correct": 105,
      "fp_normal_as_attack": 2,
      "fn_attack_as_normal": 13,
      "tp_attack_correct": 715408
    },
    {
      "track": "B_balanced_controlled_1_to_1",
      "model": "dummy_majority",
      "tn_normal_correct": 107,
      "fp_normal_as_attack": 0,
      "fn_attack_as_normal": 107,
      "tp_attack_correct": 0
    },
    {
      "track": "B_balanced_controlled_1_to_1",
      "model": "gaussian_nb",
      "tn_normal_correct": 78,
      "fp_normal_as_attack": 29,
      "fn_attack_as_normal": 0,
      "tp_attack_correct": 107
    },
    {
      "track": "B_balanced_controlled_1_to_1",
      "model": "sgd_logistic",
      "tn_normal_correct": 107,
      "fp_normal_as_attack": 0,
      "fn_attack_as_normal": 2,
      "tp_attack_correct": 105
    },
    {
      "track": "B_balanced_controlled_1_to_1",
      "model": "decision_tree",
      "tn_normal_correct": 107,
      "fp_normal_as_attack": 0,
      "fn_attack_as_normal": 1,
      "tp_attack_correct": 106
    },
    {
      "track": "B_balanced_controlled_1_to_1",
      "model": "random_forest",
      "tn_normal_correct": 107,
      "fp_normal_as_attack": 0,
      "fn_attack_as_normal": 0,
      "tp_attack_correct": 107
    },
    {
      "track": "C_balanced_controlled_1_to_2",
      "model": "dummy_majority",
      "tn_normal_correct": 0,
      "fp_normal_as_attack": 107,
      "fn_attack_as_normal": 0,
      "tp_attack_correct": 214
    },
    {
      "track": "C_balanced_controlled_1_to_2",
      "model": "gaussian_nb",
      "tn_normal_correct": 90,
      "fp_normal_as_attack": 17,
      "fn_attack_as_normal": 0,
      "tp_attack_correct": 214
    },
    {
      "track": "C_balanced_controlled_1_to_2",
      "model": "sgd_logistic",
      "tn_normal_correct": 107,
      "fp_normal_as_attack": 0,
      "fn_attack_as_normal": 4,
      "tp_attack_correct": 210
    },
    {
      "track": "C_balanced_controlled_1_to_2",
      "model": "decision_tree",
      "tn_normal_correct": 107,
      "fp_normal_as_attack": 0,
      "fn_attack_as_normal": 3,
      "tp_attack_correct": 211
    },
    {
      "track": "C_balanced_controlled_1_to_2",
      "model": "random_forest",
      "tn_normal_correct": 107,
      "fp_normal_as_attack": 0,
      "fn_attack_as_normal": 0,
      "tp_attack_correct": 214
    }
  ],
  "feature_importance": [],
  "baseline_summary": {
    "generated_at_utc": "2026-04-29T04:23:53.377249+00:00",
    "phase": "Fase 4 — Baseline Modeling",
    "source_data_dir": "data/raw/bot-iot-hf",
    "target_definition": {
      "normal": 0,
      "dos_or_ddos": 1,
      "other_attack_policy": "excluded_from_primary_binary_baseline"
    },
    "candidate_features": [
      "proto",
      "stddev",
      "N_IN_Conn_P_SrcIP",
      "min",
      "state_number",
      "mean",
      "N_IN_Conn_P_DstIP",
      "drate",
      "srate",
      "max"
    ],
    "excluded_columns": [
      "attack",
      "category",
      "subcategory",
      "pkSeqID",
      "seq",
      "saddr",
      "sport",
      "daddr",
      "dport"
    ],
    "tracks_requested": [
      "all"
    ],
    "models_requested": [
      "all"
    ],
    "random_state": 42,
    "sample_limited": false,
    "metric_policy": "Do not use accuracy as the primary claim; prioritize macro F1, MCC, balanced accuracy, recall_normal, recall_attack, confusion matrix, and FP/FN discussion.",
    "best_by_track": {
      "B_balanced_controlled_1_to_1": {
        "track": "B_balanced_controlled_1_to_1",
        "model": "random_forest",
        "model_display_name": "Random Forest",
        "model_family": "ensemble_baseline",
        "train_rows": 740,
        "train_normal_rows": 370,
        "train_dos_or_ddos_rows": 370,
        "test_rows": 214,
        "test_normal_rows": 107,
        "test_dos_or_ddos_rows": 107,
        "fit_seconds": 0.4681,
        "predict_seconds": 0.054,
        "random_state": 42,
        "sample_limited": false,
        "tn": 107,
        "fp": 0,
        "fn": 0,
        "tp": 107,
        "accuracy": 1.0,
        "balanced_accuracy": 1.0,
        "precision_attack": 1.0,
        "recall_attack": 1.0,
        "f1_attack": 1.0,
        "precision_normal": 1.0,
        "recall_normal": 1.0,
        "f1_normal": 1.0,
        "macro_f1": 1.0,
        "weighted_f1": 1.0,
        "mcc": 1.0,
        "false_positive_rate": 0.0,
        "false_negative_rate": 0.0
      },
      "C_balanced_controlled_1_to_2": {
        "track": "C_balanced_controlled_1_to_2",
        "model": "random_forest",
        "model_display_name": "Random Forest",
        "model_family": "ensemble_baseline",
        "train_rows": 1110,
        "train_normal_rows": 370,
        "train_dos_or_ddos_rows": 740,
        "test_rows": 321,
        "test_normal_rows": 107,
        "test_dos_or_ddos_rows": 214,
        "fit_seconds": 0.4595,
        "predict_seconds": 0.0572,
        "random_state": 42,
        "sample_limited": false,
        "tn": 107,
        "fp": 0,
        "fn": 0,
        "tp": 214,
        "accuracy": 1.0,
        "balanced_accuracy": 1.0,
        "precision_attack": 1.0,
        "recall_attack": 1.0,
        "f1_attack": 1.0,
        "precision_normal": 1.0,
        "recall_normal": 1.0,
        "f1_normal": 1.0,
        "macro_f1": 1.0,
        "weighted_f1": 1.0,
        "mcc": 1.0,
        "false_positive_rate": 0.0,
        "false_negative_rate": 0.0
      },
      "A_realistic_imbalanced": {
        "track": "A_realistic_imbalanced",
        "model": "decision_tree",
        "model_display_name": "Decision Tree",
        "model_family": "tree_baseline",
        "train_rows": 2861833,
        "train_normal_rows": 370,
        "train_dos_or_ddos_rows": 2861463,
        "test_rows": 715528,
        "test_normal_rows": 107,
        "test_dos_or_ddos_rows": 715421,
        "fit_seconds": 8.4656,
        "predict_seconds": 0.2353,
        "random_state": 42,
        "sample_limited": false,
        "tn": 105,
        "fp": 2,
        "fn": 13,
        "tp": 715408,
        "accuracy": 0.99997904,
        "balanced_accuracy": 0.99064512,
        "precision_attack": 0.9999972,
        "recall_attack": 0.99998183,
        "f1_attack": 0.99998952,
        "precision_normal": 0.88983051,
        "recall_normal": 0.98130841,
        "f1_normal": 0.93333333,
        "macro_f1": 0.96666142,
        "weighted_f1": 0.99997955,
        "mcc": 0.93444061,
        "false_positive_rate": 0.01869159,
        "false_negative_rate": 1.817e-05
      }
    },
    "best_overall_by_macro_f1_mcc": {
      "track": "B_balanced_controlled_1_to_1",
      "model": "random_forest",
      "model_display_name": "Random Forest",
      "model_family": "ensemble_baseline",
      "train_rows": 740,
      "train_normal_rows": 370,
      "train_dos_or_ddos_rows": 370,
      "test_rows": 214,
      "test_normal_rows": 107,
      "test_dos_or_ddos_rows": 107,
      "fit_seconds": 0.4681,
      "predict_seconds": 0.054,
      "random_state": 42,
      "sample_limited": false,
      "tn": 107,
      "fp": 0,
      "fn": 0,
      "tp": 107,
      "accuracy": 1.0,
      "balanced_accuracy": 1.0,
      "precision_attack": 1.0,
      "recall_attack": 1.0,
      "f1_attack": 1.0,
      "precision_normal": 1.0,
      "recall_normal": 1.0,
      "f1_normal": 1.0,
      "macro_f1": 1.0,
      "weighted_f1": 1.0,
      "mcc": 1.0,
      "false_positive_rate": 0.0,
      "false_negative_rate": 0.0
    },
    "total_completed_runs": 14,
    "skipped_runs": [
      {
        "track": "A_realistic_imbalanced",
        "model": "random_forest",
        "reason": "Skipped by default to avoid excessive runtime on full imbalanced split; controlled tracks still run this model."
      }
    ],
    "outputs": {
      "tables": [
        "results/tables/baseline_model_metrics.csv",
        "results/tables/baseline_confusion_matrices.csv",
        "results/tables/baseline_dataset_tracks.csv",
        "results/tables/baseline_label_consistency_checks.csv",
        "results/tables/baseline_skipped_runs.csv"
      ],
      "figures": [
        "results/figures/baseline_macro_f1_comparison.png",
        "results/figures/baseline_mcc_comparison.png",
        "results/figures/baseline_confusion_matrix_grid.png"
      ]
    }
  },
  "forensic_notes": [
    "Fase 3 menyiapkan dua jalur eksperimen: distribusi asli yang sangat imbalanced dan controlled balanced subset untuk mitigasi normal class kecil.",
    "Hasil forensik detail akan diisi setelah feature importance dan error analysis tersedia."
  ]
}